black_isort_hook/__init__.py
black_isort_hook/hook.py
black_isort_hook/install.py
black_isort_hook-0.1.2.dist-info/METADATA
black_isort_hook-0.1.2.dist-info/WHEEL
black_isort_hook-0.1.2.dist-info/entry_points.txt
black_isort_hook-0.1.2.dist-info/RECORD
