Metadata-Version: 2.1
Name: black-isort-hook
Version: 0.1.2
Summary: A simple pre-commit hook to run black and isort on staged files
License: MIT
Author: Victor Kotseruba
Author-email: barbuzaster@gmail.com
Requires-Python: >=3.9,<4.0
Classifier: License :: OSI Approved :: MIT License
Classifier: Programming Language :: Python :: 3
Classifier: Programming Language :: Python :: 3.9
Classifier: Programming Language :: Python :: 3.10
Classifier: Programming Language :: Python :: 3.11
Requires-Dist: black
Requires-Dist: isort
